xldashboard/__init__.py
xldashboard/apps.py
xldashboard/controllers.py
xldashboard/jazzmin_default.py
xldashboard/migrations/__init__.py
xldashboard/routes/__init__.py
xldashboard/routes/api.py
xldashboard/static/admin/css/admin.css
xldashboard/static/admin/css/admin.css.map
xldashboard/static/admin/css/admin.sass
xldashboard/static/admin/css/admin.sass~
xldashboard/static/admin/css/jazzmin.css
xldashboard/static/admin/css/jazzmin.css.map
xldashboard/static/admin/css/jazzmin.sass
xldashboard/static/admin/css/jazzmin.sass~
xldashboard/static/admin/css/simple-sidebar.css
xldashboard/static/admin/css/simple-sidebar.css~
xldashboard/static/admin/css/wide-classes.css
xldashboard/static/admin/js/jazzmin.js
xldashboard/static/admin/js/simple-sidebar.js
xldashboard/static/admin/js/simple-sidebar.js~
xldashboard/static/img/icon/logo.png
xldashboard/static/jazzmin/css/main.css
xldashboard/static/jazzmin/img/icon/user.png
xldashboard/templates/admin/base.html
xldashboard/templates/admin/base.html~
xldashboard/templates/admin/change_form.html
xldashboard/templates/admin/index.html
xldashboard/templates/xl_dashboard/xl_dashboard.html
xldashboard/templatetags/__init__.py
xldashboard/templatetags/xl_dashboard_tags.py
xldashboard-0.2.0.dist-info/licenses/LICENSE
xldashboard-0.2.0.dist-info/METADATA
xldashboard-0.2.0.dist-info/WHEEL
xldashboard-0.2.0.dist-info/top_level.txt
xldashboard-0.2.0.dist-info/RECORD
