Metadata-Version: 2.4
Name: xldashboard
Version: 0.2.0
Summary: More beautiful/customizable admin dashboard for Django
Home-page: https://github.com/Artasov/xldashboard
Author: xlartas
Author-email: ivanhvalevskey@gmail.com
Project-URL: Source, https://github.com/Artasov/xldashboard 
Project-URL: Tracker, https://github.com/Artasov/xldashboard /issues
Keywords: dashboard django app apps jazzmin xldashboard utils admin beautiful funcs features
Classifier: Framework :: Django
Classifier: Framework :: Django :: 4
Classifier: Framework :: Django :: 4.1
Classifier: Framework :: Django :: 4.2
Classifier: Framework :: Django :: 5
Classifier: Framework :: Django :: 5.1
Classifier: Framework :: Django :: 5.2
Classifier: Framework :: Django :: 6.0
Classifier: Programming Language :: Python :: 3.8
Classifier: Programming Language :: Python :: 3.9
Classifier: Programming Language :: Python :: 3.10
Classifier: Programming Language :: Python :: 3.11
Classifier: Programming Language :: Python :: 3.12
Classifier: Programming Language :: Python :: 3.13
Classifier: Programming Language :: Python :: 3.14
Classifier: Operating System :: OS Independent
Classifier: License :: OSI Approved :: MIT License
Classifier: Intended Audience :: Developers
Classifier: Topic :: Software Development :: Libraries :: Application Frameworks
Requires-Python: >=3.8
License-File: LICENSE
Requires-Dist: Django>=4.0
Requires-Dist: django-jazzmin>=3.0.1
Requires-Dist: pyperclip>=1.8.0
Requires-Dist: aiohttp>=3.8.0
Requires-Dist: celery>=5.0.0
Dynamic: author
Dynamic: author-email
Dynamic: classifier
Dynamic: description
Dynamic: description-content-type
Dynamic: home-page
Dynamic: keywords
Dynamic: license-file
Dynamic: project-url
Dynamic: requires-dist
Dynamic: requires-python
Dynamic: summary
